moonworm/__init__.py
moonworm/abi.py
moonworm/cli.py
moonworm/contracts.py
moonworm/deployment.py
moonworm/manage.py
moonworm/version.py
moonworm/watch.py
moonworm/web3_util.py
moonworm/__pycache__/__init__.cpython-38.pyc
moonworm/__pycache__/version.cpython-38.pyc
moonworm/crawler/__init__.py
moonworm/crawler/ethereum_state_provider.py
moonworm/crawler/example.py
moonworm/crawler/function_call_crawler.py
moonworm/crawler/log_scanner.py
moonworm/crawler/moonstream_ethereum_state_provider.py
moonworm/crawler/networks.py
moonworm/crawler/state/__init__.py
moonworm/crawler/state/event_scanner_state.py
moonworm/crawler/state/json_state.py
moonworm/crawler/state/moonstream_event_state.py
moonworm/crawler/state/sqlite_state.py
moonworm/fixture/abis/CUContract.json
moonworm/fixture/abis/CULands.json
moonworm/fixture/abis/CryptoKitties.json
moonworm/fixture/abis/DiamondCutFacet.json
moonworm/fixture/abis/Greeter.json
moonworm/fixture/abis/OpenseaDAOProxy.json
moonworm/fixture/abis/OpenseaExchange.json
moonworm/fixture/abis/OpenseaProxyRegistry.json
moonworm/fixture/abis/OpenseaToken.json
moonworm/fixture/abis/OwnableERC1155.json
moonworm/fixture/abis/OwnableERC20.json
moonworm/fixture/abis/OwnableERC721.json
moonworm/fixture/bytecodes/Greeter.bin
moonworm/fixture/bytecodes/OpenseaDAOProxy.bin
moonworm/fixture/bytecodes/OpenseaExchange.bin
moonworm/fixture/bytecodes/OpenseaProxyRegistry.bin
moonworm/fixture/bytecodes/OpenseaToken.bin
moonworm/fixture/bytecodes/OwnableERC1155.bin
moonworm/fixture/bytecodes/OwnableERC20.bin
moonworm/fixture/bytecodes/OwnableERC721.bin
moonworm/fixture/events_abi/events.sample.json
moonworm/fixture/smart_contracts/Greeter.sol
moonworm/fixture/smart_contracts/OwnableERC1155.sol
moonworm/fixture/smart_contracts/OwnableERC20.sol
moonworm/fixture/smart_contracts/OwnableERC721.sol
moonworm/fixture/smart_contracts/compile.sh
moonworm/generators/__init__.py
moonworm/generators/basic.py
moonworm/generators/brownie.py
moonworm-0.9.3.dist-info/LICENSE
moonworm-0.9.3.dist-info/METADATA
moonworm-0.9.3.dist-info/WHEEL
moonworm-0.9.3.dist-info/entry_points.txt
moonworm-0.9.3.dist-info/top_level.txt
moonworm-0.9.3.dist-info/RECORD
