Metadata-Version: 2.1
Name: moonworm
Version: 0.9.3
Summary: moonworm: Generate a command line interface to any Ethereum smart contract
Home-page: https://github.com/moonstream-to/moonworm/
Author: Moonstream
Author-email: engineering@moonstream.to
License: UNKNOWN
Platform: UNKNOWN
Classifier: Development Status :: 3 - Alpha
Classifier: Programming Language :: Python
Classifier: License :: OSI Approved :: Apache Software License
Classifier: Topic :: Software Development :: Libraries
Requires-Python: >=3.6
Requires-Dist: black
Requires-Dist: inflection
Requires-Dist: libcst
Requires-Dist: tqdm
Requires-Dist: typing-extensions
Requires-Dist: web3 >=5.27.0
Requires-Dist: pysha3 <2.0.0,>=1.0.0 ; python_version < "3.6"
Provides-Extra: dev
Requires-Dist: isort ; extra == 'dev'
Requires-Dist: mypy ; extra == 'dev'
Requires-Dist: wheel ; extra == 'dev'
Requires-Dist: web3 >=5.27.0 ; extra == 'dev'
Provides-Extra: distribute
Requires-Dist: setuptools ; extra == 'distribute'
Requires-Dist: twine ; extra == 'distribute'
Requires-Dist: wheel ; extra == 'distribute'
Provides-Extra: moonstream
Requires-Dist: moonstreamdb >=0.3.3 ; extra == 'moonstream'
Requires-Dist: moonstream-types >=0.0.3 ; extra == 'moonstream'
